simplelayout/__init__.py
simplelayout/__main__.py
simplelayout/cli/__init__.py
simplelayout/cli/cli_generate.py
simplelayout/generator/__init__.py
simplelayout/generator/core.py
simplelayout/generator/utils.py
simplelayout_Vincentius1990-0.0.2.dist-info/METADATA
simplelayout_Vincentius1990-0.0.2.dist-info/WHEEL
simplelayout_Vincentius1990-0.0.2.dist-info/entry_points.txt
simplelayout_Vincentius1990-0.0.2.dist-info/top_level.txt
simplelayout_Vincentius1990-0.0.2.dist-info/RECORD
