Metadata-Version: 2.1
Name: simplelayout-Vincentius1990
Version: 0.0.2
Summary: A small example package
Home-page: UNKNOWN
Author: Vincentius1990
Author-email: vincent1990@126.com
License: UNKNOWN
Platform: UNKNOWN
Requires-Dist: matplotlib
Requires-Dist: numpy
Requires-Dist: scipy
